{
  "Major": 0,
  "Minor": 1,
  "Patch": 0,
  "PreReleaseTag": "mouse-layer.1",
  "PreReleaseTagWithDash": "-mouse-layer.1",
  "PreReleaseLabel": "mouse-layer",
  "PreReleaseLabelWithDash": "-mouse-layer",
  "PreReleaseNumber": 1,
  "WeightedPreReleaseNumber": 30001,
  "BuildMetaData": 4,
  "BuildMetaDataPadded": "0004",
  "FullBuildMetaData": "4.Branch.feature-mouse-layer.Sha.e2c342f6fee361f5a81d3e643e18ce0f586ec3bc",
  "MajorMinorPatch": "0.1.0",
  "SemVer": "0.1.0-mouse-layer.1",
  "LegacySemVer": "0.1.0-mouse-layer1",
  "LegacySemVerPadded": "0.1.0-mouse-layer0001",
  "AssemblySemVer": "0.1.0.0",
  "AssemblySemFileVer": "0.1.0.0",
  "FullSemVer": "0.1.0-mouse-layer.1+4",
  "InformationalVersion": "0.1.0-mouse-layer.1+4.Branch.feature-mouse-layer.Sha.e2c342f6fee361f5a81d3e643e18ce0f586ec3bc",
  "BranchName": "feature/mouse-layer",
  "EscapedBranchName": "feature-mouse-layer",
  "Sha": "e2c342f6fee361f5a81d3e643e18ce0f586ec3bc",
  "ShortSha": "e2c342f",
  "NuGetVersionV2": "0.1.0-mouse-layer0001",
  "NuGetVersion": "0.1.0-mouse-layer0001",
  "NuGetPreReleaseTagV2": "mouse-layer0001",
  "NuGetPreReleaseTag": "mouse-layer0001",
  "VersionSourceSha": "1f989568a9ed51fda37d7cb531ada740e873fdc7",
  "CommitsSinceVersionSource": 4,
  "CommitsSinceVersionSourcePadded": "0004",
  "UncommittedChanges": 1,
  "CommitDate": "2024-09-25"
}